Workbook

Sheet README
A1: Finance Performance Model: Data Book
A2: Exported from the Power BI model 'finance project'. Amounts are in the model's reporting currency.
A4: Sheet | B4: Contents
A5: Monthly_Data | B5: Month x account detail, actual and budget (432 rows), with favourable-positive variance formulas
A6: PL_Monthly | B6: Monthly P&L built with SUMIFS from Monthly_Data, actual vs budget, through the last actual month
A7: Region_Summary | B7: Actual and budget by region and account group, through the last actual month
A8: Forecast | B8: Oct-Dec 2026 forecast with lower and upper bounds, as stored in the model
A9: Forecast_Backtest | B9: Forecast methods ranked by MAPE (lower is better)
A10: Scenario_Slicer | B10: Revenue adjustment values used by the what-if slicer
A11: Dim_Account | B11: Account list, group and P&L order
A13: Conventions | B13: Blue text = values exported from the model. Black = formulas.
A14: Last actual month | B14: Sep 2026. Oct-Dec 2026 have budget only.
A15: Variance sign | B15: Favourable is positive: revenue = actual - budget; costs = budget - actual.
A16: Net profit | B16: EBITDA - D&A - interest - tax, matching the model's [Net Profit] measure.
A17: Grain note | B17: Monthly_Data is summed across regions. Region detail is on Region_Summary.

Sheet Monthly_Data
A1: Month | B1: Year | C1: Month No | D1: Account | E1: Account Group | F1: Actual | G1: Budget | H1: Variance (Fav +) | I1: Variance %
A2: 45292 | B2: =YEAR(A2) -> 2024 | C2: =MONTH(A2) -> 1 | D2: Product Revenue | E2: Revenue | F2: 10751289 | G2: 10752924 | H2: =IF(F2="","",IF(E2="Revenue",F2-G2,G2-F2)) -> -1635 | I2: =IF(OR(F2="",G2=0),"",H2/G2) -> -0.00015205167
A3: 45292 | B3: =YEAR(A3) -> 2024 | C3: =MONTH(A3) -> 1 | D3: Service Revenue | E3: Revenue | F3: 3618704 | G3: 3584307 | H3: =IF(F3="","",IF(E3="Revenue",F3-G3,G3-F3)) -> 34397 | I3: =IF(OR(F3="",G3=0),"",H3/G3) -> 0.0095965552
A4: 45292 | B4: =YEAR(A4) -> 2024 | C4: =MONTH(A4) -> 1 | D4: Cost of Goods Sold | E4: COGS | F4: 5665929 | G4: 5555677 | H4: =IF(F4="","",IF(E4="Revenue",F4-G4,G4-F4)) -> -110252 | I4: =IF(OR(F4="",G4=0),"",H4/G4) -> -0.019844926
A5: 45292 | B5: =YEAR(A5) -> 2024 | C5: =MONTH(A5) -> 1 | D5: Direct Labor | E5: COGS | F5: 1559905 | G5: 1500000 | H5: =IF(F5="","",IF(E5="Revenue",F5-G5,G5-F5)) -> -59905 | I5: =IF(OR(F5="",G5=0),"",H5/G5) -> -0.039936667
A6: 45292 | B6: =YEAR(A6) -> 2024 | C6: =MONTH(A6) -> 1 | D6: Salaries & Wages | E6: Operating Expenses | F6: 3570429 | G6: 3500000 | H6: =IF(F6="","",IF(E6="Revenue",F6-G6,G6-F6)) -> -70429 | I6: =IF(OR(F6="",G6=0),"",H6/G6) -> -0.020122571
A7: 45292 | B7: =YEAR(A7) -> 2024 | C7: =MONTH(A7) -> 1 | D7: Marketing & Advertising | E7: Operating Expenses | F7: 1239301 | G7: 1200000 | H7: =IF(F7="","",IF(E7="Revenue",F7-G7,G7-F7)) -> -39301 | I7: =IF(OR(F7="",G7=0),"",H7/G7) -> -0.032750833
A8: 45292 | B8: =YEAR(A8) -> 2024 | C8: =MONTH(A8) -> 1 | D8: Rent & Utilities | E8: Operating Expenses | F8: 600000 | G8: 600000 | H8: =IF(F8="","",IF(E8="Revenue",F8-G8,G8-F8)) -> 0 | I8: =IF(OR(F8="",G8=0),"",H8/G8) -> 0
A9: 45292 | B9: =YEAR(A9) -> 2024 | C9: =MONTH(A9) -> 1 | D9: Software & IT | E9: Operating Expenses | F9: 459110 | G9: 450000 | H9: =IF(F9="","",IF(E9="Revenue",F9-G9,G9-F9)) -> -9110 | I9: =IF(OR(F9="",G9=0),"",H9/G9) -> -0.020244444
A10: 45292 | B10: =YEAR(A10) -> 2024 | C10: =MONTH(A10) -> 1 | D10: Travel & Entertainment | E10: Operating Expenses | F10: 264941 | G10: 300000 | H10: =IF(F10="","",IF(E10="Revenue",F10-G10,G10-F10)) -> 35059 | I10: =IF(OR(F10="",G10=0),"",H10/G10) -> 0.11686333
A11: 45292 | B11: =YEAR(A11) -> 2024 | C11: =MONTH(A11) -> 1 | D11: Depreciation & Amortization | E11: D&A | F11: 400000 | G11: 400000 | H11: =IF(F11="","",IF(E11="Revenue",F11-G11,G11-F11)) -> 0 | I11: =IF(OR(F11="",G11=0),"",H11/G11) -> 0
A12: 45292 | B12: =YEAR(A12) -> 2024 | C12: =MONTH(A12) -> 1 | D12: Interest Expense | E12: Interest | F12: 257500 | G12: 250000 | H12: =IF(F12="","",IF(E12="Revenue",F12-G12,G12-F12)) -> -7500 | I12: =IF(OR(F12="",G12=0),"",H12/G12) -> -0.03
A13: 45292 | B13: =YEAR(A13) -> 2024 | C13: =MONTH(A13) -> 1 | D13: Income Tax | E13: Tax | F13: 94587 | G13: 145389 | H13: =IF(F13="","",IF(E13="Revenue",F13-G13,G13-F13)) -> 50802 | I13: =IF(OR(F13="",G13=0),"",H13/G13) -> 0.34942121
... A397: 46266 | B397: =YEAR(A397) -> 2026 | C397: =MONTH(A397) -> 9 | D397: Income Tax | E397: Tax | F397: 846875 | G397: 1391990 | H397: =IF(F397="","",IF(E397="Revenue",F397-G397,G397-F397)) -> 545115 | I397: =IF(OR(F397="",G397=0),"",H397/G397) -> 0.39160842
A398: 46296 | B398: =YEAR(A398) -> 2026 | C398: =MONTH(A398) -> 10 | D398: Product Revenue | E398: Revenue | G398: 18436926 | H398: =IF(F398="","",IF(E398="Revenue",F398-G398,G398-F398)) | I398: =IF(OR(F398="",G398=0),"",H398/G398)
A399: 46296 | B399: =YEAR(A399) -> 2026 | C399: =MONTH(A399) -> 10 | D399: Service Revenue | E399: Revenue | G399: 6145642 | H399: =IF(F399="","",IF(E399="Revenue",F399-G399,G399-F399)) | I399: =IF(OR(F399="",G399=0),"",H399/G399)
A400: 46296 | B400: =YEAR(A400) -> 2026 | C400: =MONTH(A400) -> 10 | D400: Cost of Goods Sold | E400: COGS | G400: 9525744 | H400: =IF(F400="","",IF(E400="Revenue",F400-G400,G400-F400)) | I400: =IF(OR(F400="",G400=0),"",H400/G400)
A401: 46296 | B401: =YEAR(A401) -> 2026 | C401: =MONTH(A401) -> 10 | D401: Direct Labor | E401: COGS | G401: 2083036 | H401: =IF(F401="","",IF(E401="Revenue",F401-G401,G401-F401)) | I401: =IF(OR(F401="",G401=0),"",H401/G401)
A402: 46296 | B402: =YEAR(A402) -> 2026 | C402: =MONTH(A402) -> 10 | D402: Salaries & Wages | E402: Operating Expenses | G402: 4263844 | H402: =IF(F402="","",IF(E402="Revenue",F402-G402,G402-F402)) | I402: =IF(OR(F402="",G402=0),"",H402/G402)
A403: 46296 | B403: =YEAR(A403) -> 2026 | C403: =MONTH(A403) -> 10 | D403: Marketing & Advertising | E403: Operating Expenses | G403: 1666427 | H403: =IF(F403="","",IF(E403="Revenue",F403-G403,G403-F403)) | I403: =IF(OR(F403="",G403=0),"",H403/G403)
A404: 46296 | B404: =YEAR(A404) -> 2026 | C404: =MONTH(A404) -> 10 | D404: Rent & Utilities | E404: Operating Expenses | G404: 640893 | H404: =IF(F404="","",IF(E404="Revenue",F404-G404,G404-F404)) | I404: =IF(OR(F404="",G404=0),"",H404/G404)
A405: 46296 | B405: =YEAR(A405) -> 2026 | C405: =MONTH(A405) -> 10 | D405: Software & IT | E405: Operating Expenses | G405: 585343 | H405: =IF(F405="","",IF(E405="Revenue",F405-G405,G405-F405)) | I405: =IF(OR(F405="",G405=0),"",H405/G405)
A406: 46296 | B406: =YEAR(A406) -> 2026 | C406: =MONTH(A406) -> 10 | D406: Travel & Entertainment | E406: Operating Expenses | G406: 353673 | H406: =IF(F406="","",IF(E406="Revenue",F406-G406,G406-F406)) | I406: =IF(OR(F406="",G406=0),"",H406/G406)
A407: 46296 | B407: =YEAR(A407) -> 2026 | C407: =MONTH(A407) -> 10 | D407: Depreciation & Amortization | E407: D&A | G407: 441560 | H407: =IF(F407="","",IF(E407="Revenue",F407-G407,G407-F407)) | I407: =IF(OR(F407="",G407=0),"",H407/G407)
A408: 46296 | B408: =YEAR(A408) -> 2026 | C408: =MONTH(A408) -> 10 | D408: Interest Expense | E408: Interest | G408: 250000 | H408: =IF(F408="","",IF(E408="Revenue",F408-G408,G408-F408)) | I408: =IF(OR(F408="",G408=0),"",H408/G408)
A409: 46296 | B409: =YEAR(A409) -> 2026 | C409: =MONTH(A409) -> 10 | D409: Income Tax | E409: Tax | G409: 1193013 | H409: =IF(F409="","",IF(E409="Revenue",F409-G409,G409-F409)) | I409: =IF(OR(F409="",G409=0),"",H409/G409)
... A433: 46357 | B433: =YEAR(A433) -> 2026 | C433: =MONTH(A433) -> 12 | D433: Income Tax | E433: Tax | G433: 1023042 | H433: =IF(F433="","",IF(E433="Revenue",F433-G433,G433-F433)) | I433: =IF(OR(F433="",G433=0),"",H433/G433)

Sheet PL_Monthly
A1: Monthly P&L: Actual vs Budget
A2: Built from Monthly_Data with SUMIFS. Covers Jan 2024 to Sep 2026 (months with actuals).
A4: Month | B4: Revenue | C4: COGS | D4: Gross Profit | E4: Gross Margin % | F4: Operating Expenses | G4: EBITDA | H4: EBITDA Margin % | I4: D&A | J4: EBIT | K4: Interest | L4: Tax | M4: Net Profit | N4: Net Margin % | O4: Budget Revenue | P4: Budget Net Profit | Q4: Revenue Var % | R4: Net Profit Var %
A5: 45292 | B5: =SUMIFS(Monthly_Data!$F$2:$F$433,Monthly_Data!$A$2:$A$433,$A5,Monthly_Data!$E$2:$E$433,"Revenue") -> 14369993 | C5: =SUMIFS(Monthly_Data!$F$2:$F$433,Monthly_Data!$A$2:$A$433,$A5,Monthly_Data!$E$2:$E$433,"COGS") -> 7225834 | D5: =B5-C5 -> 7144159 | E5: =IF(B5=0,0,D5/B5) -> 0.49715814 | F5: =SUMIFS(Monthly_Data!$F$2:$F$433,Monthly_Data!$A$2:$A$433,$A5,Monthly_Data!$E$2:$E$433,"Operating Expenses") -> 6133781 | G5: =D5-F5 -> 1010378 | H5: =IF(B5=0,0,G5/B5) -> 0.070311656 | I5: =SUMIFS(Monthly_Data!$F$2:$F$433,Monthly_Data!$A$2:$A$433,$A5,Monthly_Data!$E$2:$E$433,"D&A") -> 400000 | J5: =G5-I5 -> 610378 | K5: =SUMIFS(Monthly_Data!$F$2:$F$433,Monthly_Data!$A$2:$A$433,$A5,Monthly_Data!$E$2:$E$433,"Interest") -> 257500 | L5: =SUMIFS(Monthly_Data!$F$2:$F$433,Monthly_Data!$A$2:$A$433,$A5,Monthly_Data!$E$2:$E$433,"Tax") -> 94587 | M5: =J5-K5-L5 -> 258291 | N5: =IF(B5=0,0,M5/B5) -> 0.01797433 | O5: =SUMIFS(Monthly_Data!$G$2:$G$433,Monthly_Data!$A$2:$A$433,$A5,Monthly_Data!$E$2:$E$433,"Revenue") -> 14337231 | P5: =SUMIFS(Monthly_Data!$G$2:$G$433,Monthly_Data!$A$2:$A$433,$A5,Monthly_Data!$E$2:$E$433,"Revenue")-SUMIFS(Monthly_Data!$G$2:$G$433,Monthly_Data!$A$2:$A$433,$A5,Monthly_Data!$E$2:$E$433,"<>Revenue") -> 436165 | Q5: =IF(O5=0,0,(B5-O5)/O5) -> 0.0022850995 | R5: =IF(P5=0,0,(M5-P5)/ABS(P5)) -> -0.40781356
A6: 45323 | B6: =SUMIFS(Monthly_Data!$F$2:$F$433,Monthly_Data!$A$2:$A$433,$A6,Monthly_Data!$E$2:$E$433,"Revenue") -> 15095460 | C6: =SUMIFS(Monthly_Data!$F$2:$F$433,Monthly_Data!$A$2:$A$433,$A6,Monthly_Data!$E$2:$E$433,"COGS") -> 7486463 | D6: =B6-C6 -> 7608997 | E6: =IF(B6=0,0,D6/B6) -> 0.50405864 | F6: =SUMIFS(Monthly_Data!$F$2:$F$433,Monthly_Data!$A$2:$A$433,$A6,Monthly_Data!$E$2:$E$433,"Operating Expenses") -> 6174144 | G6: =D6-F6 -> 1434853 | H6: =IF(B6=0,0,G6/B6) -> 0.095051956 | I6: =SUMIFS(Monthly_Data!$F$2:$F$433,Monthly_Data!$A$2:$A$433,$A6,Monthly_Data!$E$2:$E$433,"D&A") -> 401200 | J6: =G6-I6 -> 1033653 | K6: =SUMIFS(Monthly_Data!$F$2:$F$433,Monthly_Data!$A$2:$A$433,$A6,Monthly_Data!$E$2:$E$433,"Interest") -> 257876 | L6: =SUMIFS(Monthly_Data!$F$2:$F$433,Monthly_Data!$A$2:$A$433,$A6,Monthly_Data!$E$2:$E$433,"Tax") -> 193944 | M6: =J6-K6-L6 -> 581833 | N6: =IF(B6=0,0,M6/B6) -> 0.038543575 | O6: =SUMIFS(Monthly_Data!$G$2:$G$433,Monthly_Data!$A$2:$A$433,$A6,Monthly_Data!$E$2:$E$433,"Revenue") -> 15265600 | P6: =SUMIFS(Monthly_Data!$G$2:$G$433,Monthly_Data!$A$2:$A$433,$A6,Monthly_Data!$E$2:$E$433,"Revenue")-SUMIFS(Monthly_Data!$G$2:$G$433,Monthly_Data!$A$2:$A$433,$A6,Monthly_Data!$E$2:$E$433,"<>Revenue") -> 821009 | Q6: =IF(O6=0,0,(B6-O6)/O6) -> -0.01114532 | R6: =IF(P6=0,0,(M6-P6)/ABS(P6)) -> -0.29131958
A7: 45352 | B7: =SUMIFS(Monthly_Data!$F$2:$F$433,Monthly_Data!$A$2:$A$433,$A7,Monthly_Data!$E$2:$E$433,"Revenue") -> 16236794 | C7: =SUMIFS(Monthly_Data!$F$2:$F$433,Monthly_Data!$A$2:$A$433,$A7,Monthly_Data!$E$2:$E$433,"COGS") -> 7925285 | D7: =B7-C7 -> 8311509 | E7: =IF(B7=0,0,D7/B7) -> 0.51189348 | F7: =SUMIFS(Monthly_Data!$F$2:$F$433,Monthly_Data!$A$2:$A$433,$A7,Monthly_Data!$E$2:$E$433,"Operating Expenses") -> 6223599 | G7: =D7-F7 -> 2087910 | H7: =IF(B7=0,0,G7/B7) -> 0.12859127 | I7: =SUMIFS(Monthly_Data!$F$2:$F$433,Monthly_Data!$A$2:$A$433,$A7,Monthly_Data!$E$2:$E$433,"D&A") -> 402404 | J7: =G7-I7 -> 1685506 | K7: =SUMIFS(Monthly_Data!$F$2:$F$433,Monthly_Data!$A$2:$A$433,$A7,Monthly_Data!$E$2:$E$433,"Interest") -> 258251 | L7: =SUMIFS(Monthly_Data!$F$2:$F$433,Monthly_Data!$A$2:$A$433,$A7,Monthly_Data!$E$2:$E$433,"Tax") -> 356813 | M7: =J7-K7-L7 -> 1070442 | N7: =IF(B7=0,0,M7/B7) -> 0.065926931 | O7: =SUMIFS(Monthly_Data!$G$2:$G$433,Monthly_Data!$A$2:$A$433,$A7,Monthly_Data!$E$2:$E$433,"Revenue") -> 16483600 | P7: =SUMIFS(Monthly_Data!$G$2:$G$433,Monthly_Data!$A$2:$A$433,$A7,Monthly_Data!$E$2:$E$433,"Revenue")-SUMIFS(Monthly_Data!$G$2:$G$433,Monthly_Data!$A$2:$A$433,$A7,Monthly_Data!$E$2:$E$433,"<>Revenue") -> 1338572 | Q7: =IF(O7=0,0,(B7-O7)/O7) -> -0.014972821 | R7: =IF(P7=0,0,(M7-P7)/ABS(P7)) -> -0.20031048
A8: 45383 | B8: =SUMIFS(Monthly_Data!$F$2:$F$433,Monthly_Data!$A$2:$A$433,$A8,Monthly_Data!$E$2:$E$433,"Revenue") -> 17196464 | C8: =SUMIFS(Monthly_Data!$F$2:$F$433,Monthly_Data!$A$2:$A$433,$A8,Monthly_Data!$E$2:$E$433,"COGS") -> 8284402 | D8: =B8-C8 -> 8912062 | E8: =IF(B8=0,0,D8/B8) -> 0.51824968 | F8: =SUMIFS(Monthly_Data!$F$2:$F$433,Monthly_Data!$A$2:$A$433,$A8,Monthly_Data!$E$2:$E$433,"Operating Expenses") -> 6269420 | G8: =D8-F8 -> 2642642 | H8: =IF(B8=0,0,G8/B8) -> 0.15367357 | I8: =SUMIFS(Monthly_Data!$F$2:$F$433,Monthly_Data!$A$2:$A$433,$A8,Monthly_Data!$E$2:$E$433,"D&A") -> 403611 | J8: =G8-I8 -> 2239031 | K8: =SUMIFS(Monthly_Data!$F$2:$F$433,Monthly_Data!$A$2:$A$433,$A8,Monthly_Data!$E$2:$E$433,"Interest") -> 258626 | L8: =SUMIFS(Monthly_Data!$F$2:$F$433,Monthly_Data!$A$2:$A$433,$A8,Monthly_Data!$E$2:$E$433,"Tax") -> 495101 | M8: =J8-K8-L8 -> 1485304 | N8: =IF(B8=0,0,M8/B8) -> 0.08637264 | O8: =SUMIFS(Monthly_Data!$G$2:$G$433,Monthly_Data!$A$2:$A$433,$A8,Monthly_Data!$E$2:$E$433,"Revenue") -> 17734705 | P8: =SUMIFS(Monthly_Data!$G$2:$G$433,Monthly_Data!$A$2:$A$433,$A8,Monthly_Data!$E$2:$E$433,"Revenue")-SUMIFS(Monthly_Data!$G$2:$G$433,Monthly_Data!$A$2:$A$433,$A8,Monthly_Data!$E$2:$E$433,"<>Revenue") -> 1871015 | Q8: =IF(O8=0,0,(B8-O8)/O8) -> -0.030349589 | R8: =IF(P8=0,0,(M8-P8)/ABS(P8)) -> -0.20615067
A9: 45413 | B9: =SUMIFS(Monthly_Data!$F$2:$F$433,Monthly_Data!$A$2:$A$433,$A9,Monthly_Data!$E$2:$E$433,"Revenue") -> 18187428 | C9: =SUMIFS(Monthly_Data!$F$2:$F$433,Monthly_Data!$A$2:$A$433,$A9,Monthly_Data!$E$2:$E$433,"COGS") -> 8742543 | D9: =B9-C9 -> 9444885 | E9: =IF(B9=0,0,D9/B9) -> 0.51930845 | F9: =SUMIFS(Monthly_Data!$F$2:$F$433,Monthly_Data!$A$2:$A$433,$A9,Monthly_Data!$E$2:$E$433,"Operating Expenses") -> 6322846 | G9: =D9-F9 -> 3122039 | H9: =IF(B9=0,0,G9/B9) -> 0.17165918 | I9: =SUMIFS(Monthly_Data!$F$2:$F$433,Monthly_Data!$A$2:$A$433,$A9,Monthly_Data!$E$2:$E$433,"D&A") -> 404820 | J9: =G9-I9 -> 2717219 | K9: =SUMIFS(Monthly_Data!$F$2:$F$433,Monthly_Data!$A$2:$A$433,$A9,Monthly_Data!$E$2:$E$433,"Interest") -> 259000 | L9: =SUMIFS(Monthly_Data!$F$2:$F$433,Monthly_Data!$A$2:$A$433,$A9,Monthly_Data!$E$2:$E$433,"Tax") -> 614556 | M9: =J9-K9-L9 -> 1843663 | N9: =IF(B9=0,0,M9/B9) -> 0.10137019 | O9: =SUMIFS(Monthly_Data!$G$2:$G$433,Monthly_Data!$A$2:$A$433,$A9,Monthly_Data!$E$2:$E$433,"Revenue") -> 18746618 | P9: =SUMIFS(Monthly_Data!$G$2:$G$433,Monthly_Data!$A$2:$A$433,$A9,Monthly_Data!$E$2:$E$433,"Revenue")-SUMIFS(Monthly_Data!$G$2:$G$433,Monthly_Data!$A$2:$A$433,$A9,Monthly_Data!$E$2:$E$433,"<>Revenue") -> 2293244 | Q9: =IF(O9=0,0,(B9-O9)/O9) -> -0.029828847 | R9: =IF(P9=0,0,(M9-P9)/ABS(P9)) -> -0.19604586
A10: 45444 | B10: =SUMIFS(Monthly_Data!$F$2:$F$433,Monthly_Data!$A$2:$A$433,$A10,Monthly_Data!$E$2:$E$433,"Revenue") -> 18794290 | C10: =SUMIFS(Monthly_Data!$F$2:$F$433,Monthly_Data!$A$2:$A$433,$A10,Monthly_Data!$E$2:$E$433,"COGS") -> 8993821 | D10: =B10-C10 -> 9800469 | E10: =IF(B10=0,0,D10/B10) -> 0.52145992 | F10: =SUMIFS(Monthly_Data!$F$2:$F$433,Monthly_Data!$A$2:$A$433,$A10,Monthly_Data!$E$2:$E$433,"Operating Expenses") -> 6372793 | G10: =D10-F10 -> 3427676 | H10: =IF(B10=0,0,G10/B10) -> 0.18237858 | I10: =SUMIFS(Monthly_Data!$F$2:$F$433,Monthly_Data!$A$2:$A$433,$A10,Monthly_Data!$E$2:$E$433,"D&A") -> 406036 | J10: =G10-I10 -> 3021640 | K10: =SUMIFS(Monthly_Data!$F$2:$F$433,Monthly_Data!$A$2:$A$433,$A10,Monthly_Data!$E$2:$E$433,"Interest") -> 259376 | L10: =SUMIFS(Monthly_Data!$F$2:$F$433,Monthly_Data!$A$2:$A$433,$A10,Monthly_Data!$E$2:$E$433,"Tax") -> 690566 | M10: =J10-K10-L10 -> 2071698 | N10: =IF(B10=0,0,M10/B10) -> 0.11023018 | O10: =SUMIFS(Monthly_Data!$G$2:$G$433,Monthly_Data!$A$2:$A$433,$A10,Monthly_Data!$E$2:$E$433,"Revenue") -> 19304930 | P10: =SUMIFS(Monthly_Data!$G$2:$G$433,Monthly_Data!$A$2:$A$433,$A10,Monthly_Data!$E$2:$E$433,"Revenue")-SUMIFS(Monthly_Data!$G$2:$G$433,Monthly_Data!$A$2:$A$433,$A10,Monthly_Data!$E$2:$E$433,"<>Revenue") -> 2506760 | Q10: =IF(O10=0,0,(B10-O10)/O10) -> -0.026451274 | R10: =IF(P10=0,0,(M10-P10)/ABS(P10)) -> -0.17355551
A11: 45474 | B11: =SUMIFS(Monthly_Data!$F$2:$F$433,Monthly_Data!$A$2:$A$433,$A11,Monthly_Data!$E$2:$E$433,"Revenue") -> 18793061 | C11: =SUMIFS(Monthly_Data!$F$2:$F$433,Monthly_Data!$A$2:$A$433,$A11,Monthly_Data!$E$2:$E$433,"COGS") -> 9063581 | D11: =B11-C11 -> 9729480 | E11: =IF(B11=0,0,D11/B11) -> 0.51771662 | F11: =SUMIFS(Monthly_Data!$F$2:$F$433,Monthly_Data!$A$2:$A$433,$A11,Monthly_Data!$E$2:$E$433,"Operating Expenses") -> 6421298 | G11: =D11-F11 -> 3308182 | H11: =IF(B11=0,0,G11/B11) -> 0.1760321 | I11: =SUMIFS(Monthly_Data!$F$2:$F$433,Monthly_Data!$A$2:$A$433,$A11,Monthly_Data!$E$2:$E$433,"D&A") -> 407254 | J11: =G11-I11 -> 2900928 | K11: =SUMIFS(Monthly_Data!$F$2:$F$433,Monthly_Data!$A$2:$A$433,$A11,Monthly_Data!$E$2:$E$433,"Interest") -> 259751 | L11: =SUMIFS(Monthly_Data!$F$2:$F$433,Monthly_Data!$A$2:$A$433,$A11,Monthly_Data!$E$2:$E$433,"Tax") -> 660294 | M11: =J11-K11-L11 -> 1980883 | N11: =IF(B11=0,0,M11/B11) -> 0.10540502 | O11: =SUMIFS(Monthly_Data!$G$2:$G$433,Monthly_Data!$A$2:$A$433,$A11,Monthly_Data!$E$2:$E$433,"Revenue") -> 19313236 | P11: =SUMIFS(Monthly_Data!$G$2:$G$433,Monthly_Data!$A$2:$A$433,$A11,Monthly_Data!$E$2:$E$433,"Revenue")-SUMIFS(Monthly_Data!$G$2:$G$433,Monthly_Data!$A$2:$A$433,$A11,Monthly_Data!$E$2:$E$433,"<>Revenue") -> 2467280 | Q11: =IF(O11=0,0,(B11-O11)/O11) -> -0.026933601 | R11: =IF(P11=0,0,(M11-P11)/ABS(P11)) -> -0.19713895
A12: 45505 | B12: =SUMIFS(Monthly_Data!$F$2:$F$433,Monthly_Data!$A$2:$A$433,$A12,Monthly_Data!$E$2:$E$433,"Revenue") -> 18345813 | C12: =SUMIFS(Monthly_Data!$F$2:$F$433,Monthly_Data!$A$2:$A$433,$A12,Monthly_Data!$E$2:$E$433,"COGS") -> 8835897 | D12: =B12-C12 -> 9509916 | E12: =IF(B12=0,0,D12/B12) -> 0.51836983 | F12: =SUMIFS(Monthly_Data!$F$2:$F$433,Monthly_Data!$A$2:$A$433,$A12,Monthly_Data!$E$2:$E$433,"Operating Expenses") -> 6472957 | G12: =D12-F12 -> 3036959 | H12: =IF(B12=0,0,G12/B12) -> 0.16553962 | I12: =SUMIFS(Monthly_Data!$F$2:$F$433,Monthly_Data!$A$2:$A$433,$A12,Monthly_Data!$E$2:$E$433,"D&A") -> 408476 | J12: =G12-I12 -> 2628483 | K12: =SUMIFS(Monthly_Data!$F$2:$F$433,Monthly_Data!$A$2:$A$433,$A12,Monthly_Data!$E$2:$E$433,"Interest") -> 260126 | L12: =SUMIFS(Monthly_Data!$F$2:$F$433,Monthly_Data!$A$2:$A$433,$A12,Monthly_Data!$E$2:$E$433,"Tax") -> 592090 | M12: =J12-K12-L12 -> 1776267 | N12: =IF(B12=0,0,M12/B12) -> 0.096821384 | O12: =SUMIFS(Monthly_Data!$G$2:$G$433,Monthly_Data!$A$2:$A$433,$A12,Monthly_Data!$E$2:$E$433,"Revenue") -> 18822970 | P12: =SUMIFS(Monthly_Data!$G$2:$G$433,Monthly_Data!$A$2:$A$433,$A12,Monthly_Data!$E$2:$E$433,"Revenue")-SUMIFS(Monthly_Data!$G$2:$G$433,Monthly_Data!$A$2:$A$433,$A12,Monthly_Data!$E$2:$E$433,"<>Revenue") -> 2198424 | Q12: =IF(O12=0,0,(B12-O12)/O12) -> -0.025349719 | R12: =IF(P12=0,0,(M12-P12)/ABS(P12)) -> -0.19202711
A13: 45536 | B13: =SUMIFS(Monthly_Data!$F$2:$F$433,Monthly_Data!$A$2:$A$433,$A13,Monthly_Data!$E$2:$E$433,"Revenue") -> 17237400 | C13: =SUMIFS(Monthly_Data!$F$2:$F$433,Monthly_Data!$A$2:$A$433,$A13,Monthly_Data!$E$2:$E$433,"COGS") -> 8407287 | D13: =B13-C13 -> 8830113 | E13: =IF(B13=0,0,D13/B13) -> 0.51226478 | F13: =SUMIFS(Monthly_Data!$F$2:$F$433,Monthly_Data!$A$2:$A$433,$A13,Monthly_Data!$E$2:$E$433,"Operating Expenses") -> 6520790 | G13: =D13-F13 -> 2309323 | H13: =IF(B13=0,0,G13/B13) -> 0.13397165 | I13: =SUMIFS(Monthly_Data!$F$2:$F$433,Monthly_Data!$A$2:$A$433,$A13,Monthly_Data!$E$2:$E$433,"D&A") -> 409700 | J13: =G13-I13 -> 1899623 | K13: =SUMIFS(Monthly_Data!$F$2:$F$433,Monthly_Data!$A$2:$A$433,$A13,Monthly_Data!$E$2:$E$433,"Interest") -> 260500 | L13: =SUMIFS(Monthly_Data!$F$2:$F$433,Monthly_Data!$A$2:$A$433,$A13,Monthly_Data!$E$2:$E$433,"Tax") -> 409781 | M13: =J13-K13-L13 -> 1229342 | N13: =IF(B13=0,0,M13/B13) -> 0.071318296 | O13: =SUMIFS(Monthly_Data!$G$2:$G$433,Monthly_Data!$A$2:$A$433,$A13,Monthly_Data!$E$2:$E$433,"Revenue") -> 18023882 | P13: =SUMIFS(Monthly_Data!$G$2:$G$433,Monthly_Data!$A$2:$A$433,$A13,Monthly_Data!$E$2:$E$433,"Revenue")-SUMIFS(Monthly_Data!$G$2:$G$433,Monthly_Data!$A$2:$A$433,$A13,Monthly_Data!$E$2:$E$433,"<>Revenue") -> 1787357 | Q13: =IF(O13=0,0,(B13-O13)/O13) -> -0.04363555 | R13: =IF(P13=0,0,(M13-P13)/ABS(P13)) -> -0.3122012
A14: 45566 | B14: =SUMIFS(Monthly_Data!$F$2:$F$433,Monthly_Data!$A$2:$A$433,$A14,Monthly_Data!$E$2:$E$433,"Revenue") -> 16508143 | C14: =SUMIFS(Monthly_Data!$F$2:$F$433,Monthly_Data!$A$2:$A$433,$A14,Monthly_Data!$E$2:$E$433,"COGS") -> 8167866 | D14: =B14-C14 -> 8340277 | E14: =IF(B14=0,0,D14/B14) -> 0.505222 | F14: =SUMIFS(Monthly_Data!$F$2:$F$433,Monthly_Data!$A$2:$A$433,$A14,Monthly_Data!$E$2:$E$433,"Operating Expenses") -> 6576640 | G14: =D14-F14 -> 1763637 | H14: =IF(B14=0,0,G14/B14) -> 0.10683437 | I14: =SUMIFS(Monthly_Data!$F$2:$F$433,Monthly_Data!$A$2:$A$433,$A14,Monthly_Data!$E$2:$E$433,"D&A") -> 410931 | J14: =G14-I14 -> 1352706 | K14: =SUMIFS(Monthly_Data!$F$2:$F$433,Monthly_Data!$A$2:$A$433,$A14,Monthly_Data!$E$2:$E$433,"Interest") -> 260876 | L14: =SUMIFS(Monthly_Data!$F$2:$F$433,Monthly_Data!$A$2:$A$433,$A14,Monthly_Data!$E$2:$E$433,"Tax") -> 272958 | M14: =J14-K14-L14 -> 818872 | N14: =IF(B14=0,0,M14/B14) -> 0.049604126 | O14: =SUMIFS(Monthly_Data!$G$2:$G$433,Monthly_Data!$A$2:$A$433,$A14,Monthly_Data!$E$2:$E$433,"Revenue") -> 17196587 | P14: =SUMIFS(Monthly_Data!$G$2:$G$433,Monthly_Data!$A$2:$A$433,$A14,Monthly_Data!$E$2:$E$433,"Revenue")-SUMIFS(Monthly_Data!$G$2:$G$433,Monthly_Data!$A$2:$A$433,$A14,Monthly_Data!$E$2:$E$433,"<>Revenue") -> 1362984 | Q14: =IF(O14=0,0,(B14-O14)/O14) -> -0.040033758 | R14: =IF(P14=0,0,(M14-P14)/ABS(P14)) -> -0.39920645
A15: 45597 | B15: =SUMIFS(Monthly_Data!$F$2:$F$433,Monthly_Data!$A$2:$A$433,$A15,Monthly_Data!$E$2:$E$433,"Revenue") -> 15922623 | C15: =SUMIFS(Monthly_Data!$F$2:$F$433,Monthly_Data!$A$2:$A$433,$A15,Monthly_Data!$E$2:$E$433,"COGS") -> 7992930 | D15: =B15-C15 -> 7929693 | E15: =IF(B15=0,0,D15/B15) -> 0.49801424 | F15: =SUMIFS(Monthly_Data!$F$2:$F$433,Monthly_Data!$A$2:$A$433,$A15,Monthly_Data!$E$2:$E$433,"Operating Expenses") -> 6628862 | G15: =D15-F15 -> 1300831 | H15: =IF(B15=0,0,G15/B15) -> 0.081697029 | I15: =SUMIFS(Monthly_Data!$F$2:$F$433,Monthly_Data!$A$2:$A$433,$A15,Monthly_Data!$E$2:$E$433,"D&A") -> 412163 | J15: =G15-I15 -> 888668 | K15: =SUMIFS(Monthly_Data!$F$2:$F$433,Monthly_Data!$A$2:$A$433,$A15,Monthly_Data!$E$2:$E$433,"Interest") -> 261251 | L15: =SUMIFS(Monthly_Data!$F$2:$F$433,Monthly_Data!$A$2:$A$433,$A15,Monthly_Data!$E$2:$E$433,"Tax") -> 156855 | M15: =J15-K15-L15 -> 470562 | N15: =IF(B15=0,0,M15/B15) -> 0.029553045 | O15: =SUMIFS(Monthly_Data!$G$2:$G$433,Monthly_Data!$A$2:$A$433,$A15,Monthly_Data!$E$2:$E$433,"Revenue") -> 16638943 | P15: =SUMIFS(Monthly_Data!$G$2:$G$433,Monthly_Data!$A$2:$A$433,$A15,Monthly_Data!$E$2:$E$433,"Revenue")-SUMIFS(Monthly_Data!$G$2:$G$433,Monthly_Data!$A$2:$A$433,$A15,Monthly_Data!$E$2:$E$433,"<>Revenue") -> 1062127 | Q15: =IF(O15=0,0,(B15-O15)/O15) -> -0.043050812 | R15: =IF(P15=0,0,(M15-P15)/ABS(P15)) -> -0.55696259
A16: 45627 | B16: =SUMIFS(Monthly_Data!$F$2:$F$433,Monthly_Data!$A$2:$A$433,$A16,Monthly_Data!$E$2:$E$433,"Revenue") -> 15967695 | C16: =SUMIFS(Monthly_Data!$F$2:$F$433,Monthly_Data!$A$2:$A$433,$A16,Monthly_Data!$E$2:$E$433,"COGS") -> 8032756 | D16: =B16-C16 -> 7934939 | E16: =IF(B16=0,0,D16/B16) -> 0.49693703 | F16: =SUMIFS(Monthly_Data!$F$2:$F$433,Monthly_Data!$A$2:$A$433,$A16,Monthly_Data!$E$2:$E$433,"Operating Expenses") -> 6679609 | G16: =D16-F16 -> 1255330 | H16: =IF(B16=0,0,G16/B16) -> 0.078616857 | I16: =SUMIFS(Monthly_Data!$F$2:$F$433,Monthly_Data!$A$2:$A$433,$A16,Monthly_Data!$E$2:$E$433,"D&A") -> 413400 | J16: =G16-I16 -> 841930 | K16: =SUMIFS(Monthly_Data!$F$2:$F$433,Monthly_Data!$A$2:$A$433,$A16,Monthly_Data!$E$2:$E$433,"Interest") -> 261626 | L16: =SUMIFS(Monthly_Data!$F$2:$F$433,Monthly_Data!$A$2:$A$433,$A16,Monthly_Data!$E$2:$E$433,"Tax") -> 145076 | M16: =J16-K16-L16 -> 435228 | N16: =IF(B16=0,0,M16/B16) -> 0.027256783 | O16: =SUMIFS(Monthly_Data!$G$2:$G$433,Monthly_Data!$A$2:$A$433,$A16,Monthly_Data!$E$2:$E$433,"Revenue") -> 16585520 | P16: =SUMIFS(Monthly_Data!$G$2:$G$433,Monthly_Data!$A$2:$A$433,$A16,Monthly_Data!$E$2:$E$433,"Revenue")-SUMIFS(Monthly_Data!$G$2:$G$433,Monthly_Data!$A$2:$A$433,$A16,Monthly_Data!$E$2:$E$433,"<>Revenue") -> 992545 | Q16: =IF(O16=0,0,(B16-O16)/O16) -> -0.037250867 | R16: =IF(P16=0,0,(M16-P16)/ABS(P16)) -> -0.561503
... A37: 46266 | B37: =SUMIFS(Monthly_Data!$F$2:$F$433,Monthly_Data!$A$2:$A$433,$A37,Monthly_Data!$E$2:$E$433,"Revenue") -> 23344825 | C37: =SUMIFS(Monthly_Data!$F$2:$F$433,Monthly_Data!$A$2:$A$433,$A37,Monthly_Data!$E$2:$E$433,"COGS") -> 11358990 | D37: =B37-C37 -> 11985835 | E37: =IF(B37=0,0,D37/B37) -> 0.51342578 | F37: =SUMIFS(Monthly_Data!$F$2:$F$433,Monthly_Data!$A$2:$A$433,$A37,Monthly_Data!$E$2:$E$433,"Operating Expenses") -> 7888596 | G37: =D37-F37 -> 4097239 | H37: =IF(B37=0,0,G37/B37) -> 0.17550952 | I37: =SUMIFS(Monthly_Data!$F$2:$F$433,Monthly_Data!$A$2:$A$433,$A37,Monthly_Data!$E$2:$E$433,"D&A") -> 440240 | J37: =G37-I37 -> 3656999 | K37: =SUMIFS(Monthly_Data!$F$2:$F$433,Monthly_Data!$A$2:$A$433,$A37,Monthly_Data!$E$2:$E$433,"Interest") -> 269500 | L37: =SUMIFS(Monthly_Data!$F$2:$F$433,Monthly_Data!$A$2:$A$433,$A37,Monthly_Data!$E$2:$E$433,"Tax") -> 846875 | M37: =J37-K37-L37 -> 2540624 | N37: =IF(B37=0,0,M37/B37) -> 0.10883029 | O37: =SUMIFS(Monthly_Data!$G$2:$G$433,Monthly_Data!$A$2:$A$433,$A37,Monthly_Data!$E$2:$E$433,"Revenue") -> 25765190 | P37: =SUMIFS(Monthly_Data!$G$2:$G$433,Monthly_Data!$A$2:$A$433,$A37,Monthly_Data!$E$2:$E$433,"Revenue")-SUMIFS(Monthly_Data!$G$2:$G$433,Monthly_Data!$A$2:$A$433,$A37,Monthly_Data!$E$2:$E$433,"<>Revenue") -> 4175971 | Q37: =IF(O37=0,0,(B37-O37)/O37) -> -0.093939342 | R37: =IF(P37=0,0,(M37-P37)/ABS(P37)) -> -0.3916088
A38: Total | B38: =SUM(B5:B37) -> 642706347 | C38: =SUM(C5:C37) -> 312637633 | D38: =SUM(D5:D37) -> 330068714 | E38: =IF(B38=0,0,D38/B38) -> 0.51356069 | F38: =SUM(F5:F37) -> 229944110 | G38: =SUM(G5:G37) -> 100124604 | H38: =IF(B38=0,0,G38/B38) -> 0.15578593 | I38: =SUM(I5:I37) -> 13853694 | J38: =SUM(J5:J37) -> 86270910 | K38: =SUM(K5:K37) -> 8695524 | L38: =SUM(L5:L37) -> 19400229 | M38: =SUM(M5:M37) -> 58175157 | N38: =IF(B38=0,0,M38/B38) -> 0.090515921 | O38: =SUM(O5:O37) -> 683593290 | P38: =SUM(P5:P37) -> 87183100 | Q38: =IF(O38=0,0,(B38-O38)/O38) -> -0.059811797 | R38: =IF(P38=0,0,(M38-P38)/ABS(P38)) -> -0.33272438

Sheet Region_Summary
A1: Region Summary: Actual vs Budget
A2: Through the last actual month (Sep 2026). Variance is favourable-positive.
A4: Region | B4: Account Group | C4: Actual | D4: Budget | E4: Variance (Fav +) | F4: Variance %
A5: East | B5: COGS | C5: 43361204 | D5: 48479388 | E5: =IF(B5="Revenue",C5-D5,D5-C5) -> 5118184 | F5: =IF(D5=0,0,E5/D5) -> 0.10557444
A6: East | B6: D&A | C6: 2078055 | D6: 2078055 | E6: =IF(B6="Revenue",C6-D6,D6-C6) -> 0 | F6: =IF(D6=0,0,E6/D6) -> 0
A7: East | B7: Interest | C7: 1304329 | D7: 1237500 | E7: =IF(B7="Revenue",C7-D7,D7-C7) -> -66829 | F7: =IF(D7=0,0,E7/D7) -> -0.054003232
A8: East | B8: Operating Expenses | C8: 34491035 | D8: 33307426 | E8: =IF(B8="Revenue",C8-D8,D8-C8) -> -1183609 | F8: =IF(D8=0,0,E8/D8) -> -0.035535889
A9: East | B9: Revenue | C9: 90392718 | D9: 102538996 | E9: =IF(B9="Revenue",C9-D9,D9-C9) -> -12146278 | F9: =IF(D9=0,0,E9/D9) -> -0.11845521
A10: East | B10: Tax | C10: 2295898 | D10: 4359164 | E10: =IF(B10="Revenue",C10-D10,D10-C10) -> 2063266 | F10: =IF(D10=0,0,E10/D10) -> 0.4733169
A11: North | B11: COGS | C11: 92793774 | D11: 96958772 | E11: =IF(B11="Revenue",C11-D11,D11-C11) -> 4164998 | F11: =IF(D11=0,0,E11/D11) -> 0.042956382
A12: North | B12: D&A | C12: 4156107 | D12: 4156107 | E12: =IF(B12="Revenue",C12-D12,D12-C12) -> 0 | F12: =IF(D12=0,0,E12/D12) -> 0
A13: North | B13: Interest | C13: 2608658 | D13: 2475000 | E13: =IF(B13="Revenue",C13-D13,D13-C13) -> -133658 | F13: =IF(D13=0,0,E13/D13) -> -0.054003232
A14: North | B14: Operating Expenses | C14: 68984496 | D14: 66614861 | E14: =IF(B14="Revenue",C14-D14,D14-C14) -> -2369635 | F14: =IF(D14=0,0,E14/D14) -> -0.035572168
A15: North | B15: Revenue | C15: 191150649 | D15: 205077984 | E15: =IF(B15="Revenue",C15-D15,D15-C15) -> -13927335 | F15: =IF(D15=0,0,E15/D15) -> -0.067912385
A16: North | B16: Tax | C16: 5651908 | D16: 8718315 | E16: =IF(B16="Revenue",C16-D16,D16-C16) -> 3066407 | F16: =IF(D16=0,0,E16/D16) -> 0.35172014
... A28: West | B28: Tax | C28: 5063865 | D28: 7265265 | E28: =IF(B28="Revenue",C28-D28,D28-C28) -> 2201400 | F28: =IF(D28=0,0,E28/D28) -> 0.3030034

Sheet Forecast
A1: Forecast Data
A2: Stored in the model's ForecastData table.
A4: Month | B4: Metric | C4: Method | D4: Forecast | E4: Lower | F4: Upper
A5: 46296 | B5: Net Profit | C5: Holt-Winters (damped) | D5: 2148529 | E5: 1950936 | F5: 2346121
A6: 46327 | B6: Net Profit | C6: Holt-Winters (damped) | D6: 1761757 | E6: 1599734 | F6: 1923780
A7: 46357 | B7: Net Profit | C7: Holt-Winters (damped) | D7: 1689752 | E7: 1534351 | F7: 1845152
A8: 46296 | B8: Revenue | C8: Seasonal naive + growth | D8: 22360585 | E8: 22129332 | F8: 22591838
A9: 46327 | B9: Revenue | C9: Seasonal naive + growth | D9: 21354061 | E9: 21133218 | F9: 21574905
A10: 46357 | B10: Revenue | C10: Seasonal naive + growth | D10: 21209130 | E10: 20989786 | F10: 21428475
A12: Q4 2026 total
B13: Revenue | D13: =SUMIFS(D5:D10,B5:B10,"Revenue") -> 64923776
B14: Net Profit | D14: =SUMIFS(D5:D10,B5:B10,"Net Profit") -> 5600038

Sheet Forecast_Backtest
A1: Forecast Backtest
A2: MAPE = mean absolute percentage error. Lower is better. 'Selected' is the method used in the model.
A4: Metric | B4: Method | C4: MAPE % | D4: Rank | E4: Status
A5: Net Profit | B5: Holt-Winters (damped) | C5: 6.4 | D5: 1 | E5: Selected
A6: Net Profit | B6: Regression + seasonality | C6: 7.67 | D6: 2
A7: Net Profit | B7: Seasonal naive + growth | C7: 9.83 | D7: 3
A8: Net Profit | B8: Budget x trailing ratio | C8: 12.86 | D8: 4
A9: Net Profit | B9: ARIMA(1,1,1) | C9: 22.73 | D9: 5
A10: Revenue | B10: Seasonal naive + growth | C10: 0.72 | D10: 1 | E10: Selected
A11: Revenue | B11: Budget x trailing ratio | C11: 1.41 | D11: 2
A12: Revenue | B12: Holt-Winters (damped) | C12: 2.1 | D12: 3
A13: Revenue | B13: Regression + seasonality | C13: 2.38 | D13: 4
A14: Revenue | B14: ARIMA(1,1,1) | C14: 7.73 | D14: 5

Sheet Scenario_Slicer
A1: Scenario Slicer Values
A2: Revenue adjustment applied to the Q4 forecast in the model's what-if measures.
A4: Revenue Adjustment
A5: -0.1
A6: -0.09
A7: -0.08
A8: -0.07
A9: -0.06
A10: -0.05
A11: -0.04
A12: -0.03
A13: -0.02
A14: -0.01
A15: 0
A16: 0.01
... A25: 0.1

Sheet Dim_Account
A1: Account Dimension
A2: P&L order follows the model's PLOrder column.
A4: P&L Order | B4: Account Name | C4: Account Group
A5: 1 | B5: Product Revenue | C5: Revenue
A6: 2 | B6: Service Revenue | C6: Revenue
A7: 3 | B7: Cost of Goods Sold | C7: COGS
A8: 4 | B8: Direct Labor | C8: COGS
A9: 5 | B9: Salaries & Wages | C9: Operating Expenses
A10: 6 | B10: Marketing & Advertising | C10: Operating Expenses
A11: 7 | B11: Rent & Utilities | C11: Operating Expenses
A12: 8 | B12: Software & IT | C12: Operating Expenses
A13: 9 | B13: Travel & Entertainment | C13: Operating Expenses
A14: 10 | B14: Depreciation & Amortization | C14: D&A
A15: 11 | B15: Interest Expense | C15: Interest
A16: 12 | B16: Income Tax | C16: Tax
